prime_mcp/__init__.py
prime_mcp/__main__.py
prime_mcp/operations.py
prime_mcp/server.py
prime_mcp/data/code_guideline.json
prime_mcp/data/instructions.txt
prime_mcp/data/recommendation.json
prime_mcp/data/summary.json
prime_mcp-0.1.17.dist-info/METADATA
prime_mcp-0.1.17.dist-info/WHEEL
prime_mcp-0.1.17.dist-info/entry_points.txt
prime_mcp-0.1.17.dist-info/RECORD
