Metadata-Version: 2.4
Name: prime-mcp
Version: 0.1.17
Author-email: reubinoff <moshe@primesec.ai>
Requires-Python: <4.0,>=3.13
Requires-Dist: mcp[cli]<2.0.0,>=1.6.0
Requires-Dist: pydantic-ai>=0.1.6
Requires-Dist: pydantic>=2.11.3
Requires-Dist: typer>=0.15.2
